nbclean/__init__.py
nbclean/__main__.py
nbclean/args.py
nbclean/checks.py
nbclean/path_helper.py
nbclean/utils.py
nbsexy/__init__.py
nbsexy/__main__.py
nbsexy/_checks_fun.py
nbsexy/args.py
nbsexy/checks.py
nbsexy/path_helper.py
nbsexy/utils.py
tests/__init__.py
tests/test_path_helper.py
tests/integration/__init__.py
tests/integration/test_cli.py
tests/integration/test_execute_related_cli.py
nbsexy-0.0.6.dist-info/LICENSE
nbsexy-0.0.6.dist-info/METADATA
nbsexy-0.0.6.dist-info/WHEEL
nbsexy-0.0.6.dist-info/entry_points.txt
nbsexy-0.0.6.dist-info/top_level.txt
nbsexy-0.0.6.dist-info/RECORD
