Metadata-Version: 2.1
Name: nbsexy
Version: 0.0.6
Summary: A tool to make your notebook sexier than before.
Home-page: https://github.com/hyades910739/nbsexy
Author: hyades910739
Author-email: hyades910739@gmail.com
License: UNKNOWN
Platform: UNKNOWN
Classifier: Programming Language :: Python :: 3
Classifier: License :: OSI Approved :: MIT License
Classifier: Operating System :: OS Independent
Requires-Python: >=3.6
Requires-Dist: colorama (>=0.4.4)
Requires-Dist: papermill (==2.3.4)
